onymancer/__init__.py
onymancer/namegen.py
onymancer/pronounceability.py
onymancer/data/default.json
onymancer/data/dwarvish.json
onymancer/data/elvish.json
onymancer-0.3.0.dist-info/METADATA
onymancer-0.3.0.dist-info/WHEEL
onymancer-0.3.0.dist-info/licenses/LICENSE.md
onymancer-0.3.0.dist-info/RECORD
