Metadata-Version: 2.4
Name: onymancer
Version: 0.3.0
Summary: A Python library for procedural fantasy name generation
Project-URL: Homepage, https://github.com/Galfurian/onymancer
Project-URL: Repository, https://github.com/Galfurian/onymancer
Project-URL: Issues, https://github.com/Galfurian/onymancer/issues
Project-URL: Changelog, https://github.com/Galfurian/onymancer/blob/main/CHANGELOG.md
Author-email: Enrico <enrico@example.com>
Maintainer-email: Enrico <enrico@example.com>
License: # MIT License
License-File: LICENSE.md
Keywords: fantasy,generation,name,procedural,random
Classifier: Development Status :: 3 - Alpha
Classifier: Intended Audience :: Developers
Classifier: License :: OSI Approved :: MIT License
Classifier: Programming Language :: Python :: 3
Classifier: Programming Language :: Python :: 3.8
Classifier: Programming Language :: Python :: 3.9
Classifier: Programming Language :: Python :: 3.10
Classifier: Programming Language :: Python :: 3.11
Classifier: Programming Language :: Python :: 3.12
Classifier: Topic :: Games/Entertainment
Classifier: Topic :: Utilities
Requires-Python: >=3.10
Provides-Extra: dev
Requires-Dist: black>=22.0.0; extra == 'dev'
Requires-Dist: flake8>=4.0.0; extra == 'dev'
Requires-Dist: isort>=5.10.0; extra == 'dev'
Requires-Dist: mypy>=0.950; extra == 'dev'
Requires-Dist: pytest-cov>=4.0.0; extra == 'dev'
Requires-Dist: pytest>=7.0.0; extra == 'dev'
Requires-Dist: ruff>=0.14.0; extra == 'dev'
